setup.py
mongodb_log_je.egg-info/PKG-INFO
mongodb_log_je.egg-info/SOURCES.txt
mongodb_log_je.egg-info/dependency_links.txt
mongodb_log_je.egg-info/requires.txt
mongodb_log_je.egg-info/top_level.txt
mongolog/__init__.py
mongolog/handlers.py