Metadata-Version: 1.0
Name: mongodb-log-je
Version: 0.1.0
Summary: Centralized logging made simple using mongodb
Home-page: https://github.com/andreisavu/mongodb-log/tree/master
Author: Andrei Savu
Author-email: contact@andreisavu.ro
License: UNKNOWN
Platform: UNKNOWN
